LICENSE
README.md
setup.py
pyqidian/__init__.py
pyqidian/base.py
pyqidian/open.py
pyqidian/user.py
pyqidian.egg-info/PKG-INFO
pyqidian.egg-info/SOURCES.txt
pyqidian.egg-info/dependency_links.txt
pyqidian.egg-info/requires.txt
pyqidian.egg-info/top_level.txt