Metadata-Version: 2.4
Name: pyqidian
Version: 1.0.5
Home-page: https://github.com/renqiukai/pyqidian
Author: Renqiukai
Author-email: renqiukai@qq.com
License: MIT Licence
Keywords: qidian,qidian_api
Platform: any
License-File: LICENSE
Requires-Dist: requests
Requires-Dist: loguru
Dynamic: author
Dynamic: author-email
Dynamic: home-page
Dynamic: keywords
Dynamic: license
Dynamic: license-file
Dynamic: platform
Dynamic: requires-dist
